botxbinxuser/PrincipalMetodos.py
botxbinxuser/__init__.py
botxbinxuser/responses.py
botxbinxuser/symbols.py
botxbingxuser-0.0.7.dist-info/METADATA
botxbingxuser-0.0.7.dist-info/WHEEL
botxbingxuser-0.0.7.dist-info/top_level.txt
botxbingxuser-0.0.7.dist-info/RECORD
