Metadata-Version: 2.1
Name: botxbingxuser
Version: 0.0.7
Summary: API de acesso a Xbinx
Author: Thiago Ventura
Author-email: <tigoluthi@gmail.com>
Keywords: python,first package
Classifier: Development Status :: 3 - Alpha
Classifier: Intended Audience :: Education
Classifier: Programming Language :: Python :: 2
Classifier: Programming Language :: Python :: 3
Classifier: Operating System :: MacOS :: MacOS X
Classifier: Operating System :: Microsoft :: Windows
